cipherchecks/__init__.py
cipherchecks/main.py
cipherchecks-0.1.4.dist-info/entry_points.txt
cipherchecks-0.1.4.dist-info/LICENSE
cipherchecks-0.1.4.dist-info/WHEEL
cipherchecks-0.1.4.dist-info/METADATA
cipherchecks-0.1.4.dist-info/RECORD
