Metadata-Version: 2.1
Name: cipherchecks
Version: 0.1.4
Summary: 
Author: Joe Thorpe
Author-email: joe.thorpe@orangecyberdefense.com
Requires-Python: >=3.9,<4.0
Classifier: Programming Language :: Python :: 3
Classifier: Programming Language :: Python :: 3.10
Classifier: Programming Language :: Python :: 3.9
Requires-Dist: crayons (>=0.4.0,<0.5.0)
Requires-Dist: sslyze (>=4.1.0,<5.0.0)
